ET_Client.py
LICENSE
MANIFEST.in
README.md
requirements.txt
setup.py
EventableFuelSDK/__init__.py
EventableFuelSDK/client.py
EventableFuelSDK/objects.py
EventableFuelSDK/rest.py
EventableFuelSDK/suds_patch.py
EventableFuelSDK.egg-info/PKG-INFO
EventableFuelSDK.egg-info/SOURCES.txt
EventableFuelSDK.egg-info/dependency_links.txt
EventableFuelSDK.egg-info/pbr.json
EventableFuelSDK.egg-info/requires.txt
EventableFuelSDK.egg-info/top_level.txt