Metadata-Version: 1.1
Name: EventableFuelSDK
Version: 0.1.3
Summary: ExactTarget Fuel SDK for Python, modified for Eventable
Home-page: https://github.com/eventable/FuelSDK-Python
Author: Eventable
Author-email: will@eventable.com
License: MIT
Platform: UNKNOWN
Classifier: Development Status :: 5 - Production/Stable
Classifier: Intended Audience :: Developers
Classifier: License :: OSI Approved :: MIT License
Classifier: Operating System :: OS Independent
Classifier: Topic :: Software Development :: Libraries
Classifier: Programming Language :: Python :: 2.7
